MANIFEST.in
README.txt
setup.py
src/config-sample.ini
src/rss2twitter.py
src/rss2twitter.egg-info/PKG-INFO
src/rss2twitter.egg-info/SOURCES.txt
src/rss2twitter.egg-info/dependency_links.txt
src/rss2twitter.egg-info/requires.txt
src/rss2twitter.egg-info/top_level.txt