Metadata-Version: 1.1
Name: rss2twitter
Version: 0.0.3
Summary: Checks rss feed for new posts and adds them to twitter.
Home-page: https://github.com/vrillusions/rss2twitter
Author: Todd Eddy
Author-email: vr@removethispart.vrillusions.com
License: UNKNOWN
Platform: UNKNOWN
Classifier: Programming Language :: Python
Classifier: Development Status :: 3 - Alpha
Classifier: License :: OSI Approved :: MIT License
Classifier: Operating System :: OS Independent
Classifier: Topic :: Internet
